{"content": {"suites": {"0": {"status": {"total_pass": 2, "total_skip": 0, "total_xpass": 0, "total_xfail": 0, "total_rerun": 0, "total_fail": 0, "total_error": 1}, "tests": {"0": {"status": "PASS", "message": "", "test_name": "test_login_tc001", "rerun": "0"}, "1": {"status": "PASS", "message": "", "test_name": "test_login_tc002", "rerun": "0"}, "2": {"status": "ERROR", "message": "file E:\\BITM_Online_14\\Projects\\TestAutomationBITM14\\pytestDemo\\test_fixture_demo.py, line 16\n  def test_browser_close(test_login_tc001):\nE       fixture 'test_login_tc001' not found\n>       available fixtures: LineMatcher, _config_for_test, _pytest, _sys_snapshot, cache, capfd, capfdbinary, caplog, capsys, capsysbinary, doctest_namespace, include_metadata_in_junit_xml, linecomp, metadata, monkeypatch, pytestconfig, pytester, record_property, record_testsuite_property, record_xml_attribute, recwarn, sb, test_browser_launch, testdir, testrun_uid, tmp_path, tmp_path_factory, tmpdir, tmpdir_factory, worker_id\n>       use 'pytest --fixtures [testpath]' for help on them.\n\nE:\\BITM_Online_14\\Projects\\TestAutomationBITM14\\pytestDemo\\test_fixture_demo.py:16\n", "test_name": "test_browser_close", "rerun": "0"}}, "suite_name": "pytestDemo/test_fixture_demo.py"}}}, "date": "August 04, 2022", "start_time": 1659621603.2792335, "total_suite": 1, "status": "FAIL", "status_list": {"pass": "2", "fail": "0", "skip": "0", "error": "1", "xpass": "0", "xfail": "0", "rerun": "0"}, "total_tests": "3"}